appmode/__init__.py
appmode/appmode.html
appmode/appmode_bottom.css
appmode/appmode_top.css
appmode/server_extension.py
appmode/static/gears.svg
appmode/static/main.js
appmode-1.1.0.data/data/etc/jupyter/jupyter_server_config.d/appmode.json
appmode-1.1.0.data/data/share/jupyter/nbextensions/appmode/gears.svg
appmode-1.1.0.data/data/share/jupyter/nbextensions/appmode/main.js
appmode-1.1.0.dist-info/licenses/LICENSE
appmode-1.1.0.dist-info/METADATA
appmode-1.1.0.dist-info/WHEEL
appmode-1.1.0.dist-info/top_level.txt
appmode-1.1.0.dist-info/RECORD
