Metadata-Version: 2.4
Name: appmode
Version: 1.1.0
Summary: A Jupyter extensions that turns notebooks into web applications.
Home-page: http://github.com/oschuett/appmode
Author: Ole Schuett
Author-email: ole.schuett@cp2k.org
License: MIT
Classifier: Programming Language :: Python :: 3
Classifier: Programming Language :: Python :: 3.7
Classifier: License :: OSI Approved :: MIT License
Classifier: Operating System :: OS Independent
Requires-Python: >=3.7
License-File: LICENSE
Requires-Dist: nbclassic>=1
Dynamic: author
Dynamic: author-email
Dynamic: classifier
Dynamic: home-page
Dynamic: license
Dynamic: license-file
Dynamic: requires-dist
Dynamic: requires-python
Dynamic: summary
